parachute/__init__.py
parachute/cli.py
parachute/constants.py
parachute/craft_communication.py
parachute/data_types.py
parachute/utils.py
parachute-0.4.3.dist-info/LICENSE
parachute-0.4.3.dist-info/entry_points.txt
parachute-0.4.3.dist-info/METADATA
parachute-0.4.3.dist-info/WHEEL
parachute-0.4.3.dist-info/RECORD
