Metadata-Version: 2.1
Name: parachute
Version: 0.4.3
Summary: A lifeline for ArduPilot craft.
Home-page: https://gitlab.com/stavros/parachute
License: AGPL-3.0-or-later
Author: Stavros Korokithakis
Author-email: hi@stavros.io
Requires-Python: >=3.6,<4.0
Classifier: License :: OSI Approved :: GNU Affero General Public License v3 or later (AGPLv3+)
Classifier: Programming Language :: Python :: 3
Classifier: Programming Language :: Python :: 3.6
Classifier: Programming Language :: Python :: 3.7
Classifier: Programming Language :: Python :: 3.8
Classifier: Programming Language :: Python :: 3.9
Classifier: Programming Language :: Python :: 3.10
Classifier: Programming Language :: Python :: 3.11
Requires-Dist: click (>=8,<9)
Requires-Dist: json5 (>=0.9.5,<0.10.0)
Requires-Dist: pymavlink (>=2.4.14,<3.0.0)
Requires-Dist: pyserial (>=3.5,<4.0)
Project-URL: Repository, https://gitlab.com/stavros/parachute
